{"expires":1758442281232,"value":{"code":200,"headers":{"etag":"W/\"A4rLNvGfkC\"","last-modified":"Sun, 14 Sep 2025 08:11:21 GMT","cache-control":"s-maxage=604800, stale-while-revalidate"},"body":{"prefix":"lucide","lastModified":1757568334,"aliases":{},"width":24,"height":24,"icons":{"calendar":{"body":"<g fill=\"none\" stroke=\"currentColor\" stroke-linecap=\"round\" stroke-linejoin=\"round\" stroke-width=\"2\"><path d=\"M8 2v4m8-4v4\"/><rect width=\"18\" height=\"18\" x=\"3\" y=\"4\" rx=\"2\"/><path d=\"M3 10h18\"/></g>"}}}},"mtime":1757837481304,"integrity":"maX4dISsQJ"}